djmongo/__init__.py
djmongo/decorators.py
djmongo/mongoutils.py
djmongo/oauth2_urls.py
djmongo/urls.py
djmongo/utils.py
djmongo/accounts/__init__.py
djmongo/accounts/apps.py
djmongo/accounts/auth.py
djmongo/accounts/forms.py
djmongo/accounts/httpauth.py
djmongo/accounts/models.py
djmongo/accounts/tests.py
djmongo/accounts/urls.py
djmongo/accounts/utils.py
djmongo/accounts/views.py
djmongo/accounts/migrations/__init__.py
djmongo/aggregations/__init__.py
djmongo/aggregations/admin.py
djmongo/aggregations/apps.py
djmongo/aggregations/forms.py
djmongo/aggregations/models.py
djmongo/aggregations/tests.py
djmongo/aggregations/urls.py
djmongo/aggregations/views.py
djmongo/aggregations/migrations/0001_initial.py
djmongo/aggregations/migrations/__init__.py
djmongo/console/__init__.py
djmongo/console/apps.py
djmongo/console/forms.py
djmongo/console/tests.py
djmongo/console/urls.py
djmongo/console/utils.py
djmongo/console/views.py
djmongo/console/migrations/__init__.py
djmongo/dataimport/__init__.py
djmongo/dataimport/admin.py
djmongo/dataimport/apps.py
djmongo/dataimport/forms.py
djmongo/dataimport/models.py
djmongo/dataimport/tests.py
djmongo/dataimport/urls.py
djmongo/dataimport/utils.py
djmongo/dataimport/views.py
djmongo/dataimport/migrations/0001_initial.py
djmongo/dataimport/migrations/__init__.py
djmongo/delete/__init__.py
djmongo/delete/admin.py
djmongo/delete/apps.py
djmongo/delete/forms.py
djmongo/delete/models.py
djmongo/delete/urls.py
djmongo/delete/migrations/__init__.py
djmongo/delete/views/__init__.py
djmongo/delete/views/ced.py
djmongo/delete/views/run.py
djmongo/management/__init__.py
djmongo/management/commands/__init__.py
djmongo/management/commands/_private.py
djmongo/management/commands/cron_aggregate.py
djmongo/management/commands/cron_reset_aggregate.py
djmongo/read/__init__.py
djmongo/read/admin.py
djmongo/read/apps.py
djmongo/read/forms.py
djmongo/read/models.py
djmongo/read/oauth2_urls.py
djmongo/read/tests.py
djmongo/read/urls.py
django_djmongo-0.7.9.6.dist-info/LICENSE.txt
django_djmongo-0.7.9.6.dist-info/METADATA
django_djmongo-0.7.9.6.dist-info/WHEEL
django_djmongo-0.7.9.6.dist-info/top_level.txt
django_djmongo-0.7.9.6.dist-info/RECORD
